capflow/__init__.py
capflow/py.typed
capflow/models/__init__.py
capflow/models/florence2.py
capflow/models/vlm.py
capflow/models/wd14.py
capflow/utils/__init__.py
capflow/utils/device.py
capflow/utils/exif.py
capflow/utils/image.py
capflow-0.4.0.dist-info/METADATA
capflow-0.4.0.dist-info/WHEEL
capflow-0.4.0.dist-info/licenses/LICENSE
capflow-0.4.0.dist-info/RECORD
