Metadata-Version: 2.4
Name: capflow
Version: 0.4.0
Summary: Image captioning library combining Florence2, WD14, and VLM for comprehensive image analysis
Author-email: minamik <mia@sync.dev>
License: MIT
License-File: LICENSE
Keywords: ai,computer-vision,florence2,image-captioning,vlm,wd14
Classifier: Development Status :: 3 - Alpha
Classifier: Intended Audience :: Developers
Classifier: License :: OSI Approved :: MIT License
Classifier: Programming Language :: Python :: 3
Classifier: Programming Language :: Python :: 3.12
Classifier: Topic :: Scientific/Engineering :: Artificial Intelligence
Classifier: Topic :: Software Development :: Libraries :: Python Modules
Requires-Python: >=3.12
Requires-Dist: accelerate>=0.20.0
Requires-Dist: einops>=0.7.0
Requires-Dist: huggingface-hub>=0.20.0
Requires-Dist: numpy>=1.24.0
Requires-Dist: onnxruntime-gpu>=1.16.0
Requires-Dist: opencv-python>=4.8.0
Requires-Dist: pillow>=10.0.0
Requires-Dist: pydantic-ai-slim[openai]>=0.0.14
Requires-Dist: timm>=0.9.0
Requires-Dist: torch>=2.0.0
Requires-Dist: transformers>=4.38.0
